seo_position_tracker/__init__.py
seo_position_tracker/main.py
seo_position_tracker/seo_position_tracker.py
seo_position_tracker-1.5.1.dist-info/entry_points.txt
seo_position_tracker-1.5.1.dist-info/LICENSE
seo_position_tracker-1.5.1.dist-info/METADATA
seo_position_tracker-1.5.1.dist-info/WHEEL
seo_position_tracker-1.5.1.dist-info/RECORD
