Metadata-Version: 2.1
Name: seo-position-tracker
Version: 1.5.1
Summary: A simple Python package for SEO position tracking from Google and other search engines.
Home-page: https://github.com/dimitryzub/seo-position-tracker
License: BSD-3-Clause
Author: Dimitry Zub
Author-email: dimitryzub@gmail.com
Requires-Python: >=3.8,<4.0
Classifier: Intended Audience :: Developers
Classifier: License :: OSI Approved :: BSD License
Classifier: Operating System :: MacOS
Classifier: Operating System :: Microsoft :: Windows
Classifier: Operating System :: POSIX :: Linux
Classifier: Programming Language :: Python :: 3
Classifier: Programming Language :: Python :: 3.8
Classifier: Programming Language :: Python :: 3.9
Classifier: Programming Language :: Python :: 3.10
Classifier: Programming Language :: Python :: 3.11
Classifier: Programming Language :: Python :: 3.6
Classifier: Programming Language :: Python :: 3.7
Classifier: Programming Language :: Python :: 3.8
Classifier: Programming Language :: Python :: 3.9
Requires-Dist: google-search-results (>=2.4.2,<3.0.0)
